dishastowork/aqws.py.py
TestingTestin123-1.0.0.dist-info/LICENSE.txt
TestingTestin123-1.0.0.dist-info/METADATA
TestingTestin123-1.0.0.dist-info/WHEEL
TestingTestin123-1.0.0.dist-info/entry_points.txt
TestingTestin123-1.0.0.dist-info/top_level.txt
TestingTestin123-1.0.0.dist-info/RECORD
