Metadata-Version: 2.1
Name: TestingTestin123
Version: 1.0.0
Summary: a demo
Home-page: https://github.com/darrenkhlim/TestingTestin123
Author: Kang Heng
Author-email: e0426117@u.nus.edu
License: NUS
Platform: UNKNOWN
Requires-Dist: numpy
